AutoTransform-1.1.1.post3.data/data/autotransform-docs/BEST_PRACTICES.md
AutoTransform-1.1.1.post3.data/data/autotransform-docs/COMPONENTS.md
AutoTransform-1.1.1.post3.data/data/autotransform-docs/CONTRIBUTING.md
AutoTransform-1.1.1.post3.data/data/autotransform-docs/CUSTOM_DEPLOYMENT.md
AutoTransform-1.1.1.post3.data/data/autotransform-docs/MANAGE_CHANGES.md
AutoTransform-1.1.1.post3.data/data/autotransform-docs/README.md
AutoTransform-1.1.1.post3.data/data/autotransform-docs/SCHEDULED_RUNS.md
AutoTransform-1.1.1.post3.data/data/autotransform-examples/manager.json
AutoTransform-1.1.1.post3.data/data/autotransform-examples/requirements.txt
AutoTransform-1.1.1.post3.data/data/autotransform-examples/scheduler.json
AutoTransform-1.1.1.post3.data/data/autotransform-examples/docker/Dockerfile
AutoTransform-1.1.1.post3.data/data/autotransform-examples/docker/docker_autotransform.sh
AutoTransform-1.1.1.post3.data/data/autotransform-examples/docker/entrypoint.sh
AutoTransform-1.1.1.post3.data/data/autotransform-examples/schemas/black_format.json
AutoTransform-1.1.1.post3.data/data/autotransform-examples/schemas/schema_map.json
AutoTransform-1.1.1.post3.data/data/autotransform-examples/workflows/autotransform.manage.yml
AutoTransform-1.1.1.post3.data/data/autotransform-examples/workflows/autotransform.run.yml
AutoTransform-1.1.1.post3.data/data/autotransform-examples/workflows/autotransform.schedule.yml
AutoTransform-1.1.1.post3.data/data/autotransform-examples/workflows/autotransform.update.yml
autotransform/__init__.py
autotransform/batcher/__init__.py
autotransform/batcher/base.py
autotransform/batcher/chunk.py
autotransform/batcher/codeowners.py
autotransform/batcher/directory.py
autotransform/batcher/extradata.py
autotransform/batcher/regex.py
autotransform/batcher/single.py
autotransform/change/__init__.py
autotransform/change/base.py
autotransform/change/github.py
autotransform/command/__init__.py
autotransform/command/base.py
autotransform/command/script.py
AutoTransform-1.1.1.post3.dist-info/LICENSE
AutoTransform-1.1.1.post3.dist-info/METADATA
AutoTransform-1.1.1.post3.dist-info/WHEEL
AutoTransform-1.1.1.post3.dist-info/entry_points.txt
AutoTransform-1.1.1.post3.dist-info/top_level.txt
AutoTransform-1.1.1.post3.dist-info/RECORD
