Metadata-Version: 2.1
Name: AutoTransform
Version: 1.1.1.post3
Summary: A component based framework for designing automated code modification
Home-page: https://github.com/nathro/AutoTransform
Author: Nathan Rockenbach
Author-email: nathro.software@gmail.com
Project-URL: Source, https://github.com/nathro/AutoTransform/
Project-URL: Bug Tracker, https://github.com/nathro/AutoTransform/issues
Keywords: codemod,automation,code change,codeshift,transformation,maintain
Classifier: Development Status :: 4 - Beta
Classifier: Intended Audience :: Developers
Classifier: Programming Language :: Python :: 3
Classifier: License :: OSI Approved :: MIT License
Classifier: Operating System :: OS Independent
Requires-Python: >=3.9
License-File: LICENSE
Requires-Dist: aiohttp >=3.9.4
Requires-Dist: idna >=3.7
Requires-Dist: certifi >=2024.2.2
Requires-Dist: urllib3 >=2.2.1
Requires-Dist: GitPython >=3.1.43
Requires-Dist: ghapi >=1.0.5
Requires-Dist: typing-extensions >=4.11
Requires-Dist: colorama >=0.4.6
Requires-Dist: pytz >=2024.1
Requires-Dist: pydantic >=2.7.1
Requires-Dist: libcst >=1.3.1
Requires-Dist: requests >=2.31.0
Requires-Dist: codeowners >=0.7.0
Requires-Dist: openai >=1.24.1
Requires-Dist: anthropic >=0.25.7
